{
  "O'Hare": {
    "neighborhood": "O'Hare",
  "most_common": {
    "species": "coyote",
    "probability": [
      95,
      80,
      100
    ],
    "image":"/images/coyote.png"
  },
  "less_common": [
    {
      "species": "raccoon",
      "probability": [
        80,
        60,
        85
      ]
    },
    {
      "species": "deer",
      "probability": [
        20,
        10,
        25
      ]
    }
  ]
},
"Norwood Park": {
    "neighborhood": "Norwood Park",
  "most_common": {
    "species": "raccoon",
    "probability": [
      83,
      75,
      90
    ],
    "image": "/images/raccoon.png"
  },
  "less_common": [
    {
      "species": "raccoon",
      "probability": [
        80,
        60,
        85
      ]
    },
    {
      "species": "deer",
      "probability": [
        20,
        10,
        25
      ]
    }
  ]
}}